[
  {
    "uuid": "839fddd2-e07d-58a2-9949-bf24c8dd1f0f",
    "entry": "顔ぶれ",
    "reading": {
      "primary": "かおぶれ",
      "alternatives": [],
      "is_heteronym": false
    },
    "grammar": {
      "pos": [
        "名詞"
      ],
      "ctype": null,
      "inflections": null
    },
    "definitions": [
      {
        "index": 1,
        "gloss": "personnel",
        "register": "standard",
        "nuance": null,
        "scenarios": [],
        "sensory_tags": {
          "colors": [],
          "temperature": null,
          "sounds": [],
          "emotions": []
        },
        "collocations": [],
        "examples": {
          "standard": [],
          "literary": [
            {
              "text": "さあどんな顔ぶれだか、一つ見てやろうじゃないか。",
              "citation": {
                "source": "ビジテリアン大祭",
                "author": "宮沢賢治",
                "note": "青空文庫"
              }
            },
            {
              "text": "僕には、党員の増減や、幹部の顔ぶれよりも、ひとりの人間の心の間隙のほうが気になるのです。",
              "citation": {
                "source": "惜別",
                "author": "太宰治",
                "note": "青空文庫"
              }
            },
            {
              "text": "長唄連中は、勿体ないような顔ぶれである。",
              "citation": {
                "source": "貞操問答",
                "author": "菊池寛",
                "note": "青空文庫"
              }
            },
            {
              "text": "発表文を読んでいて「ありゃりゃ」と驚かされたのは、役員の顔ぶれだ。",
              "citation": {
                "source": "青空のリスタート",
                "author": "富田倫生",
                "note": "青空文庫"
              }
            },
            {
              "text": "」　Ｄ「重苦しい顔ぶれだな。",
              "citation": {
                "source": "新興芸術派に就いての雑談",
                "author": "牧野信一",
                "note": "青空文庫"
              }
            },
            {
              "text": "旺玄社評では、上野山、岩井の二作家を二人の問題作家として採りあげたから、こゝでは余り顔ぶれを挙げない。",
              "citation": {
                "source": "小熊秀雄全集−19−",
                "author": "美術論・画論",
                "note": "青空文庫"
              }
            },
            {
              "text": "しかし従軍作家の顔ぶれを見ると、消費文学の作家丹羽文雄氏のやうな、又それと類型の作家が参加してゐるのは、自ら戦地お土産の如何なるものであるかといふことは大体想像がつく。",
              "citation": {
                "source": "小熊秀雄全集-20",
                "author": "大波小波",
                "note": "青空文庫"
              }
            },
            {
              "text": "七競馬のア抽障碍のように、最初の感じでは平凡な顔ぶれだと思って、馬券を休む気になって、レースだけを見物していると思いがけなく大穴が飛出したりする。",
              "citation": {
                "source": "競馬の一日に就いて",
                "author": "菊池寛",
                "note": "青空文庫"
              }
            },
            {
              "text": "口では云ってもその適確は期し難いが、それでも精神だけは飽くまで周到細心に、平凡の如く見えるレースの顔ぶれに秘められた番狂わせの可能性を探り、狂いそうに見えても実はそのレースの本命の確実なことを確かめる、――その精神を常に忘れざることが肝要である。",
              "citation": {
                "source": "競馬の一日に就いて",
                "author": "菊池寛",
                "note": "青空文庫"
              }
            },
            {
              "text": "定刻の午後六時までに小石川の青蛙堂へ着到すると、今夜の顔ぶれはこの間の怪談会とはよほど変わっていた。",
              "citation": {
                "source": "火薬庫",
                "author": "岡本綺堂",
                "note": "青空文庫"
              }
            },
            {
              "text": "同人の顔ぶれは、桑田、岡本、杉野、川瀬、それに僕、このほかに僕たちより一年上の井上君、芳島君が加わる。",
              "citation": {
                "source": "無名作家の日記",
                "author": "菊池寛",
                "note": "青空文庫"
              }
            },
            {
              "text": "大体にこの病棟には重い人がいるので、喉頭でどうしても臥ていられないと云うような、非常に重態の一人のほかにはあまり変った顔ぶれもなかった。",
              "citation": {
                "source": "草藪",
                "author": "鷹野つぎ",
                "note": "青空文庫"
              }
            },
            {
              "text": "眼ぼしい店ならば、その営業振りや店員の顔ぶれ、お客の筋。",
              "citation": {
                "source": "東京人の堕落時代",
                "author": "夢野久作",
                "note": "青空文庫"
              }
            },
            {
              "text": "この頃そこに立っている背広が何時も同じ顔ぶれなのでよかったが、遠くから別な顔が立っている時には、自分は歩調をゆっくりにし、帽子の向きを直し、近付く前に自分の知っている顔であるかどうかを確かめる。",
              "citation": {
                "source": "党生活者",
                "author": "小林多喜二",
                "note": "青空文庫"
              }
            },
            {
              "text": "こんな騒ぎの最中でも、猿若町の市村座と守田座はやはり五月の芝居を興行していて、市村座は例の権十郎、家橘、田之助、仲蔵などという顔ぶれで、一番目は「八犬伝」中幕は田之助が女形で「大晏寺堤」の春藤次郎右衛門をする。",
              "citation": {
                "source": "三浦老人昔話",
                "author": "岡本綺堂",
                "note": "青空文庫"
              }
            },
            {
              "text": "それでは従軍記者諸君に違いないが、いったい誰々だろうかと思って、ちょっとその顔ぶれを見に来たのですよ。",
              "citation": {
                "source": "青蛙堂鬼談",
                "author": "岡本綺堂",
                "note": "青空文庫"
              }
            },
            {
              "text": "海底調査隊員十一名の顔ぶれは、隊長ワーナー博士を始め、外に、観測者が五名、護衛の士官が二名、それから三名の記者であった。",
              "citation": {
                "source": "地球発狂事件",
                "author": "海野十三（丘丘十郎）",
                "note": "青空文庫"
              }
            },
            {
              "text": "一方が団十郎、左団次、小団次、秀調、源之助という顔ぶれに対して、千歳座は菊五郎、九蔵、松助、寿美蔵、国太郎、伝五郎という座組で、まず五分五分の勝負が付けられそうなものであったが、一方のおびただしい景気に圧倒されて、千歳座側はさんざんの敗軍であった。",
              "citation": {
                "source": "明治劇談　ランプの下にて",
                "author": "岡本綺堂",
                "note": "青空文庫"
              }
            },
            {
              "text": "わたしが覚えてからの市村座は、先代の中村｜芝翫を座頭にして、中村福助、片岡｜我童、市川権十郎、関三十郎などの顔ぶれで、我童と権十郎とが殆んどおなじような位置を占めている人気争いの両花形であった。",
              "citation": {
                "source": "明治劇談　ランプの下にて",
                "author": "岡本綺堂",
                "note": "青空文庫"
              }
            },
            {
              "text": "市村座は元地の猿若町から移転して、去年の十一月に新築開場式をおこない、市川左団次、市川権十郎、坂東｜家橘などの顔ぶれで、一番目は「賤嶽七本槍」、二番目は「松田の仇討」で華々しく開場したのであったが、それから半年も経たないうちに忽ち灰になってしまったのは、鳥越座以上の悲しむべき出来事であった。",
              "citation": {
                "source": "明治劇談　ランプの下にて",
                "author": "岡本綺堂",
                "note": "青空文庫"
              }
            },
            {
              "text": "その年の九月、歌舞伎座では団十郎、市川権十郎、福助、片岡市蔵らの顔ぶれで開場した。",
              "citation": {
                "source": "明治劇談　ランプの下にて",
                "author": "岡本綺堂",
                "note": "青空文庫"
              }
            },
            {
              "text": "定刻までに顔ぶれは揃って、長田君が如才なく席上の斡旋をしていたが、別にこうといって取留めたこともなかった。",
              "citation": {
                "source": "明治劇談　ランプの下にて",
                "author": "岡本綺堂",
                "note": "青空文庫"
              }
            },
            {
              "text": "俳優の顔ぶれは八百蔵、女寅、染五郎、新蔵、舛蔵などの青年俳優で、第一回興行は「地震加藤」と「黒船忠右衛門」と「関の扉」であったが、いずれも好評で、久しぶりで赤坂に歌舞伎の花を咲かせた。",
              "citation": {
                "source": "明治劇談　ランプの下にて",
                "author": "岡本綺堂",
                "note": "青空文庫"
              }
            },
            {
              "text": "この一座がその当時の顔ぶれを思い出すままに書いてみると、まず川上音二郎が座頭で――ここでは座長といっていた――次は藤沢浅二郎である。",
              "citation": {
                "source": "明治劇談　ランプの下にて",
                "author": "岡本綺堂",
                "note": "青空文庫"
              }
            },
            {
              "text": "前に言ったような顔ぶれの一座にあって、立派に自分の出し物をする以上、かれも一人前の名題俳優になりすましたはずであるが、その当時の芝居道では、かれが柳盛座の出身であるとか、二銭の芝居の鈍帳役者であるとかいうことが直接間接にわずらいをなして、その出世の道を塞いだ形があった。",
              "citation": {
                "source": "明治劇談　ランプの下にて",
                "author": "岡本綺堂",
                "note": "青空文庫"
              }
            },
            {
              "text": "時代によって顔ぶれの相違はあるが、かれの一座は坂東雛助、尾上多見丸などで、宮戸座よりも顔ぶれはよほど下がっていた。",
              "citation": {
                "source": "明治劇談　ランプの下にて",
                "author": "岡本綺堂",
                "note": "青空文庫"
              }
            },
            {
              "text": "そこでいよいよ決死隊のかおぶれがはりだされたが、隊員の数は、前より五名減って、十人となり、怪我をした者はみな天幕に留守番をすることとなった。",
              "citation": {
                "source": "大空魔艦",
                "author": "海野十三",
                "note": "青空文庫"
              }
            },
            {
              "text": "それに前後して、年寄、行司といったようなかおぶれが周旋している。",
              "citation": {
                "source": "大菩薩峠",
                "author": "畜生谷の巻",
                "note": "青空文庫"
              }
            },
            {
              "text": "炉辺閑談といううちに、ここへ集まる定連のかおぶれを、ざっと記して置きましょう。",
              "citation": {
                "source": "大菩薩峠",
                "author": "鈴慕の巻",
                "note": "青空文庫"
              }
            }
          ]
        }
      },
      {
        "index": 2,
        "gloss": "announcement of next day's match-ups",
        "register": "standard",
        "nuance": null,
        "scenarios": [],
        "sensory_tags": {
          "colors": [],
          "temperature": null,
          "sounds": [],
          "emotions": []
        },
        "collocations": [],
        "examples": {
          "standard": [],
          "literary": []
        }
      }
    ],
    "relations": {
      "homophones": [],
      "synonyms": [],
      "antonyms": [],
      "related": []
    },
    "meta": {
      "version": "1.0.0",
      "source": "JMdict, Aozora-Crawler, Illusions-Core",
      "updated_at": "2026-03-22T12:50:57Z",
      "freq_rank": 17234
    }
  }
]