[
  {
    "uuid": "adc549df-805c-5b42-a8de-68929e65f438",
    "entry": "アイヌ人",
    "reading": {
      "primary": "アイヌじん",
      "alternatives": [],
      "is_heteronym": false
    },
    "grammar": {
      "pos": [
        "名詞"
      ],
      "ctype": null,
      "inflections": null
    },
    "definitions": [
      {
        "index": 1,
        "gloss": "Ainu person",
        "register": "standard",
        "nuance": null,
        "scenarios": [],
        "sensory_tags": {
          "colors": [],
          "temperature": null,
          "sounds": [],
          "emotions": []
        },
        "collocations": [],
        "examples": {
          "standard": [
            {
              "text": "例句",
              "source": "幻辞"
            }
          ],
          "literary": [
            {
              "text": "我々は「サシスセソ」と「シャシシュシェショ」を別の音と聴きますけれども、アイヌ人などになると、言語の音として同じ音だと思っているのであります。",
              "citation": {
                "source": "古代国語の音韻に就いて",
                "author": "橋本進吉",
                "note": "青空文庫"
              }
            },
            {
              "text": "すなわちアイヌ人には言葉としては「シャ」でも「サ」でも同じことで、それを同じ音として考える。",
              "citation": {
                "source": "古代国語の音韻に就いて",
                "author": "橋本進吉",
                "note": "青空文庫"
              }
            },
            {
              "text": "我々は「サケ」と「シャケ」が間違ったら飛んでもない間違いを起しますが、アイヌ人は「サケ」も「シャケ」も音としては同じことなんです。",
              "citation": {
                "source": "古代国語の音韻に就いて",
                "author": "橋本進吉",
                "note": "青空文庫"
              }
            },
            {
              "text": "そこで鶏は今も土を踏みしめて歩き、鶺鴒は土を叩くように尾を打ち振るのだとアイヌ人は言い伝うと。",
              "citation": {
                "source": "十二支考",
                "author": "鶏に関する伝説",
                "note": "青空文庫"
              }
            },
            {
              "text": "星や、日、月、雲などについて種々の卜占法の口伝があるように、鳥類のある物たとえば烏などについては特殊の口碑があって、その啼き音に吉凶の意味ある物と考えられて居るが、鶏のみはこの種の口伝を持たぬとあって、あるアイヌ人が鶏の宵啼きや、牝鶏の時を作るを忌むを不審した由を記された。",
              "citation": {
                "source": "十二支考",
                "author": "鶏に関する伝説",
                "note": "青空文庫"
              }
            },
            {
              "text": "日本人は古く鶏を畜い、殊に柳田氏が言われた通り、奥羽に鶏を崇拝した痕跡多きに、その直隣りのアイヌ人がかくまで鶏に無頓著だったは奇態だが、これすなわちアイヌ人が多く雑居した奥羽地方で、鶏を神異の物と怪しんで崇拝した理由であるまいか。",
              "citation": {
                "source": "十二支考",
                "author": "鶏に関する伝説",
                "note": "青空文庫"
              }
            },
            {
              "text": "ただ北海道のアイヌ人が、日本人に圧迫されて次第に衰滅して行くように、彼等も現在の新しい東京人に押されて、衰滅の一路を辿っていることは疑われぬ。",
              "citation": {
                "source": "街頭から見た新東京の裏面",
                "author": "夢野久作",
                "note": "青空文庫"
              }
            },
            {
              "text": "アイヌ人でも美しい人は矢張り色が白く、濃い眉に深みのある瞳を持っていますから黒っぽいアイヌの平生着と、よく調和して、その背景になっている北海道の大自然と、アイヌはしっくりと合っていますから一層趣が深うございます。",
              "citation": {
                "source": "親しく見聞したアイヌの生活",
                "author": "宮本百合子",
                "note": "青空文庫"
              }
            },
            {
              "text": "家の父は、新しく鉄道を敷くために、山の中を測量に歩いていましたので、そのたんびアイヌ人を道案内にたのんでいました。",
              "citation": {
                "source": "くまと車掌",
                "author": "木内高音",
                "note": "青空文庫"
              }
            },
            {
              "text": "アイヌ人は、そんな縁故から、くまの肉を、よく、わたしの家へ持ってきてくれたものでした。",
              "citation": {
                "source": "くまと車掌",
                "author": "木内高音",
                "note": "青空文庫"
              }
            },
            {
              "text": "「エゾの名づけた利根川の岸邊に成長したエゾの五十嵐の家の子が今は西ヨーロッパまで來てゐる譯ですが、北歐のフィン人も東歐のハンガリア人もアイヌ人に近い血族ではありませんか。",
              "citation": {
                "source": "浪",
                "author": "石川三四郎",
                "note": "青空文庫"
              }
            },
            {
              "text": "また新井白石のような偉い學者は、これは昔北海道から樺太に棲んでゐた肅愼といふ民族が使用したものであらうと考へ、百年ほど前に日本へ來たシーボルドといふ西洋人は、これは昔のアイヌ人が使つたものだらうといつてをりました。",
              "citation": {
                "source": "博物館",
                "author": "濱田青陵",
                "note": "青空文庫"
              }
            },
            {
              "text": "しかしながらアイヌが消えると申しましても、アイヌ人そのものが滅亡し、世の中から失われてしまうのではありません。",
              "citation": {
                "source": "本州における蝦夷の末路",
                "author": "喜田貞吉",
                "note": "青空文庫"
              }
            },
            {
              "text": "スルガはツルガと同意語で、チアム語のチュルー（※ruh）即ち雑居人の意から出たもので、アイヌ人を指して呼んだ言葉であろうと云う。",
              "citation": {
                "source": "二、三の山名について",
                "author": "木暮理太郎",
                "note": "青空文庫"
              }
            },
            {
              "text": "日本でたとえてみれば、利尻島のアイヌ人（そんなものはいないが）の特殊料理みたようなもので、アルゼンチンでも、たいていの人は知らないそうです。",
              "citation": {
                "source": "西洋の浜焼",
                "author": "中谷宇吉郎",
                "note": "青空文庫"
              }
            },
            {
              "text": "アイヌ人地名のわかりやすい理由は明白である。",
              "citation": {
                "source": "地名の研究",
                "author": "柳田國男",
                "note": "青空文庫"
              }
            },
            {
              "text": "［自注18］バチラー博士――一九一八年、百合子十九歳のとき、アイヌ人に取材した小説「風に乗って来るコロポックル」を執筆した時、滞在したことのある英国人宣教師。",
              "citation": {
                "source": "獄中への手紙",
                "author": "一九四五年（昭和二十年）",
                "note": "青空文庫"
              }
            },
            {
              "text": "奥羽にはシトギという語がなお行われ（アイヌ人もシットギ）、またナマストギ・ニシトギという言葉もよく聴くから、或いは尋常の食物としてもこれを製することがあるのかも知らぬが、その他の地方では偶々同じ語があっても、それは只至って限られたる意味に用いられる。",
              "citation": {
                "source": "木綿以前の事",
                "author": "柳田国男",
                "note": "青空文庫"
              }
            }
          ]
        }
      }
    ],
    "relations": {
      "homophones": [],
      "synonyms": [],
      "antonyms": [],
      "related": []
    },
    "meta": {
      "version": "1.0.0",
      "source": "JMdict, Aozora-Crawler, Illusions-Core",
      "updated_at": "2026-03-22T22:30:00Z"
    }
  }
]