[
  {
    "uuid": "f6c70756-52c0-5585-8fc3-8ce3cbfd0077",
    "entry": "塩類",
    "reading": {
      "primary": "えんるい",
      "alternatives": [],
      "is_heteronym": false
    },
    "grammar": {
      "pos": [
        "名詞",
        "名詞-の形容詞"
      ],
      "ctype": null,
      "inflections": null
    },
    "definitions": [
      {
        "index": 1,
        "gloss": "salts",
        "register": "standard",
        "nuance": null,
        "scenarios": [],
        "sensory_tags": {
          "colors": [],
          "temperature": null,
          "sounds": [],
          "emotions": []
        },
        "collocations": [],
        "examples": {
          "standard": [
            {
              "text": "例句1",
              "source": "幻辞"
            },
            {
              "text": "例句2",
              "source": "幻辞"
            },
            {
              "text": "例句3",
              "source": "幻辞"
            },
            {
              "text": "例句4",
              "source": "幻辞"
            },
            {
              "text": "例句5",
              "source": "幻辞"
            },
            {
              "text": "例句6",
              "source": "幻辞"
            },
            {
              "text": "例句7",
              "source": "幻辞"
            },
            {
              "text": "例句8",
              "source": "幻辞"
            },
            {
              "text": "例句9",
              "source": "幻辞"
            },
            {
              "text": "例句10",
              "source": "幻辞"
            },
            {
              "text": "例句11",
              "source": "幻辞"
            },
            {
              "text": "例句12",
              "source": "幻辞"
            },
            {
              "text": "例句13",
              "source": "幻辞"
            },
            {
              "text": "例句14",
              "source": "幻辞"
            },
            {
              "text": "例句15",
              "source": "幻辞"
            },
            {
              "text": "例句16",
              "source": "幻辞"
            },
            {
              "text": "例句17",
              "source": "幻辞"
            },
            {
              "text": "例句18",
              "source": "幻辞"
            },
            {
              "text": "例句19",
              "source": "幻辞"
            },
            {
              "text": "例句20",
              "source": "幻辞"
            }
          ],
          "literary": [
            {
              "text": "粉の輪で思い出すのは、蒸発皿である種の塩類の溶液を煮詰めて蒸発させる時に、溶液の干上がるに従って、液面が周囲の器壁に接する境界線の所に、粉状の塩の土手ができる。",
              "citation": {
                "source": "自然界の縞模様",
                "author": "寺田寅彦",
                "note": "青空文庫"
              }
            },
            {
              "text": "これは雪の代わりに他の可溶塩類を使った実験ができる見込みである。",
              "citation": {
                "source": "自然界の縞模様",
                "author": "寺田寅彦",
                "note": "青空文庫"
              }
            },
            {
              "text": "温泉は塩類泉にや、硫黄の気の鼻を衝かぬも、病なき身の疲を医するには、いとうれし。",
              "citation": {
                "source": "層雲峡より大雪山へ",
                "author": "大町桂月",
                "note": "青空文庫"
              }
            },
            {
              "text": "それに、あそこの間歇泉は塩類泉なので、いやに執着こいやうなところがあつた。",
              "citation": {
                "source": "女の温泉",
                "author": "田山録弥",
                "note": "青空文庫"
              }
            },
            {
              "text": "このロック氏液というのは一プロセントの塩化ナトリウム、〇・二プロセントの塩化カルシウム、〇・二プロセントの塩化カリウム、〇・一プロセントの重炭酸ナトリウムの水溶液であって、ほゞ血液中の塩類成分の量に一致して居るから、心臓は血液を送りこまれて居ると同じ状態になって、その搏動を続けるのだ。",
              "citation": {
                "source": "恋愛曲線",
                "author": "小酒井不木",
                "note": "青空文庫"
              }
            },
            {
              "text": "煮沸器内の水を煮詰めてしまうと、あとには水中に溶けていた塩類と、浮遊していた固体の微粒子から成る土壌様の皮殻を残すということの経験は恐らく既に早くからあったのであろう。",
              "citation": {
                "source": "宇宙の始まり",
                "author": "スワンテ・アウグスト・アーレニウス　Svante August Arrhenius",
                "note": "青空文庫"
              }
            },
            {
              "text": "しかして――水と塩類との作用を受けて――その他の地層ができた。",
              "citation": {
                "source": "宇宙の始まり",
                "author": "スワンテ・アウグスト・アーレニウス　Svante August Arrhenius",
                "note": "青空文庫"
              }
            },
            {
              "text": "例えば墨汁に塩類を少し入れると、墨が沈澱して上澄みが出来るのは、イオンの為に墨の粒子が凝集を起こして沈澱するのである。",
              "citation": {
                "source": "墨流しの物理的研究",
                "author": "中谷宇吉郎",
                "note": "青空文庫"
              }
            },
            {
              "text": "塩類および土地の物質が多い水を使っていると常に重篤になる多くの苦しみもこの中に入るのであろう。",
              "citation": {
                "source": "食品の混ぜ物処理および調理の毒物（1820）",
                "author": "A TREATISE ON ADULTERATIONS OF FOOD, AND CULINARY POISONS",
                "note": "青空文庫"
              }
            },
            {
              "text": "あるときに硬水はそれに充満している土地の物質および塩類を材料の繊細な線維に沈殿させ、このようにして染料の柔らかさおよび華やかさを邪魔する。",
              "citation": {
                "source": "食品の混ぜ物処理および調理の毒物（1820）",
                "author": "A TREATISE ON ADULTERATIONS OF FOOD, AND CULINARY POISONS",
                "note": "青空文庫"
              }
            },
            {
              "text": "それは種のでんぷんは土地の塩類が多い水の中で完全に可溶性にならないからである。",
              "citation": {
                "source": "食品の混ぜ物処理および調理の毒物（1820）",
                "author": "A TREATISE ON ADULTERATIONS OF FOOD, AND CULINARY POISONS",
                "note": "青空文庫"
              }
            },
            {
              "text": "そしてこれらの土地の塩類の量は例によって非常に大きく変化する。",
              "citation": {
                "source": "食品の混ぜ物処理および調理の毒物（1820）",
                "author": "A TREATISE ON ADULTERATIONS OF FOOD, AND CULINARY POISONS",
                "note": "青空文庫"
              }
            },
            {
              "text": "これは一般に硬度が低く泉の水よりも大地の塩類が少なく、ふつう大気や炭酸ガスを少ししか含まない。",
              "citation": {
                "source": "食品の混ぜ物処理および調理の毒物（1820）",
                "author": "A TREATISE ON ADULTERATIONS OF FOOD, AND CULINARY POISONS",
                "note": "青空文庫"
              }
            },
            {
              "text": "しかし川のうちには岩の多い土地から出るのではなく、実際に最初はかなりの異物を含んでいて、長いあいだ豊富な耕作された平野を流れているあいだに塩類の成分について非常に純粋になるものがある。",
              "citation": {
                "source": "食品の混ぜ物処理および調理の毒物（1820）",
                "author": "A TREATISE ON ADULTERATIONS OF FOOD, AND CULINARY POISONS",
                "note": "青空文庫"
              }
            },
            {
              "text": "この検査は水中にある土地の塩類の化学的性質を区別できるものでないことは明らかである。",
              "citation": {
                "source": "食品の混ぜ物処理および調理の毒物（1820）",
                "author": "A TREATISE ON ADULTERATIONS OF FOOD, AND CULINARY POISONS",
                "note": "青空文庫"
              }
            },
            {
              "text": "しかし普通は一部が溶けないで残るが、その場合には、蒸発させることによって塩の一部が相互に変化して、蒸発させる前にはもともと水の中には存在しなかった塩類が形成されたと結論してもよいだろう。",
              "citation": {
                "source": "食品の混ぜ物処理および調理の毒物（1820）",
                "author": "A TREATISE ON ADULTERATIONS OF FOOD, AND CULINARY POISONS",
                "note": "青空文庫"
              }
            },
            {
              "text": "与えられた量の水にある塩類の重さが決まると、次のような方法でその正確な分析に進むことができるであろう。",
              "citation": {
                "source": "食品の混ぜ物処理および調理の毒物（1820）",
                "author": "A TREATISE ON ADULTERATIONS OF FOOD, AND CULINARY POISONS",
                "note": "青空文庫"
              }
            },
            {
              "text": "クリーム色の普通の陶器の釉薬は酸化鉛を含んでいることがあり酢や塩類の作用を受けやすい。",
              "citation": {
                "source": "食品の混ぜ物処理および調理の毒物（1820）",
                "author": "A TREATISE ON ADULTERATIONS OF FOOD, AND CULINARY POISONS",
                "note": "青空文庫"
              }
            },
            {
              "text": "即ち其の昆布を携へて実験室に至り浸出液を造り粘質物を除き無機塩類及びマンニットを結晶せしめて除去したるに呈味物質は依然として残液中に存し、種々之を分離せんと試みたるも其の目的を達せず、当時他の研究に多忙の際なりしかば此の専門外の実験は一時之を中止することとせり。",
              "citation": {
                "source": "「味の素」発明の動機",
                "author": "池田菊苗",
                "note": "青空文庫"
              }
            },
            {
              "text": "哲人も、死せる先祖の姿を、人類の塵の本質を成す塩類を用いる同様な方法によって、違法な降霊術によらずともその遺体を焼いた灰から呼び出すことができる。",
              "citation": {
                "source": "チャールズ・デクスター・ウォードの事件",
                "author": "H. P. ラヴクラフト　H.P.Lovecraft",
                "note": "青空文庫"
              }
            },
            {
              "text": "そこにはこう書いてあった：「獣類の本質を成す塩類を然るべく用意し保存する時には、発明の才に恵まれた者は、その研究室にノアの方舟の全体を設置し、思うがままに、獣の灰から精巧なる元来の姿を召喚することができる。",
              "citation": {
                "source": "チャールズ・デクスター・ウォードの事件",
                "author": "H. P. ラヴクラフト　H.P.Lovecraft",
                "note": "青空文庫"
              }
            },
            {
              "text": "ウィレットが同意しているのは、この種のものはウォードが不完全な塩類から呼び起こした実体の代表例であり、奴隷ないしは祭儀のために保管していたのに違いないという点のみである。",
              "citation": {
                "source": "チャールズ・デクスター・ウォードの事件",
                "author": "H. P. ラヴクラフト　H.P.Lovecraft",
                "note": "青空文庫"
              }
            },
            {
              "text": "その姿のままでないとしたら、この魔法使いの徒党が可能な限り多くの人体ないし遺体をその中へと還元しようと努めている「塩類」として保管するのはどうだろう？",
              "citation": {
                "source": "チャールズ・デクスター・ウォードの事件",
                "author": "H. P. ラヴクラフト　H.P.Lovecraft",
                "note": "青空文庫"
              }
            },
            {
              "text": "これもまた塩類であり――「護衛」の塩類でなければ、何の塩だろう？",
              "citation": {
                "source": "チャールズ・デクスター・ウォードの事件",
                "author": "H. P. ラヴクラフト　H.P.Lovecraft",
                "note": "青空文庫"
              }
            },
            {
              "text": "そしてこれらの人々の恐怖の作業は――一夜にして医師を老けさせた消えた恐怖の地下室は、不快な窖の中の餓えた怪物たちは、このような名状し難い結果を生んだ畏怖すべき祭文は、ウィレットのポケットに入っていた草書体の伝言は、書類は手紙は「塩類」や発見を巡る全ての会話は――これらが導く先は一体何処なのだろう？",
              "citation": {
                "source": "チャールズ・デクスター・ウォードの事件",
                "author": "H. P. ラヴクラフト　H.P.Lovecraft",
                "note": "青空文庫"
              }
            },
            {
              "text": "組織は鉱物質の塩類により保護さる。",
              "citation": {
                "source": "狂気の山脈にて",
                "author": "H. P. ラヴクラフト　H.P.Lovecraft",
                "note": "青空文庫"
              }
            },
            {
              "text": "無機塩類による置換はほとんど見られず、四千万年前のものであるにも拘らず内部の臓器は完全に損傷を免れていた。",
              "citation": {
                "source": "狂気の山脈にて",
                "author": "H. P. ラヴクラフト　H.P.Lovecraft",
                "note": "青空文庫"
              }
            },
            {
              "text": "塩類の湯も体に合います。",
              "citation": {
                "source": "獄中への手紙",
                "author": "一九三八年（昭和十三年）",
                "note": "青空文庫"
              }
            }
          ]
        }
      }
    ],
    "relations": {
      "homophones": [],
      "synonyms": [],
      "antonyms": [],
      "related": []
    },
    "meta": {
      "version": "1.0.0",
      "source": "JMdict, Aozora-Crawler, Illusions-Core",
      "updated_at": "2026-03-22T22:30:00Z"
    }
  }
]