[
  {
    "uuid": "f3058346-0824-58cb-b1c9-44bd5d585084",
    "entry": "お連れ",
    "reading": {
      "primary": "おつれ",
      "alternatives": [],
      "is_heteronym": false
    },
    "grammar": {
      "pos": [
        "名詞"
      ],
      "ctype": null,
      "inflections": null
    },
    "definitions": [
      {
        "index": 1,
        "gloss": "companion",
        "register": "standard",
        "nuance": null,
        "scenarios": [],
        "sensory_tags": {
          "colors": [],
          "temperature": null,
          "sounds": [],
          "emotions": []
        },
        "collocations": [],
        "examples": {
          "standard": [
            {
              "text": "例句",
              "source": "幻辞"
            }
          ],
          "literary": [
            {
              "text": "「なんだ」　「お連れ申しました。",
              "citation": {
                "source": "森の石松",
                "author": "山中貞雄",
                "note": "青空文庫"
              }
            },
            {
              "text": "石松、　「父っつあん、清水の御貸元が夜の明ける迄何処かで休みてえと仰言るから俺が家へお連れ申したんだ。",
              "citation": {
                "source": "森の石松",
                "author": "山中貞雄",
                "note": "青空文庫"
              }
            },
            {
              "text": "俺が折角……折角苦心してお連れ申したのに！",
              "citation": {
                "source": "森の石松",
                "author": "山中貞雄",
                "note": "青空文庫"
              }
            },
            {
              "text": "もうすぐお宮へお連れ申します。",
              "citation": {
                "source": "双子の星",
                "author": "宮沢賢治",
                "note": "青空文庫"
              }
            },
            {
              "text": "あなたも厭だというし、それに私も、そりゃ様子を知って居て、一所に苦労をして呉れたからッたっても、姉さんには極が悪くッて、内へお連れ申すわけには行かないしさ。",
              "citation": {
                "source": "木精（三尺角拾遺）",
                "author": "泉鏡花",
                "note": "青空文庫"
              }
            },
            {
              "text": "そのいはれより疾翔と申さるゝ、大力といふは、お徳によって、たとへ火の中水の中、たゞこの菩薩を念ずるものは、捨身大菩薩、必らず飛び込んで、お救ひになり、その浄明の天上にお連れなさる、その時火に入って身の毛一つも傷かず、水に潜って、羽、塵ほどもぬれぬといふ、そのお徳をば、大力とかう申しあげるのぢゃ。",
              "citation": {
                "source": "二十六夜",
                "author": "宮沢賢治",
                "note": "青空文庫"
              }
            },
            {
              "text": "どうか私の孫をお連れ下さいませ。",
              "citation": {
                "source": "雁の童子",
                "author": "宮沢賢治",
                "note": "青空文庫"
              }
            },
            {
              "text": "それでも、また立ち停ってしまわれましたので、母さまも出て行かれてもっと向うまでお連れになりました。",
              "citation": {
                "source": "雁の童子",
                "author": "宮沢賢治",
                "note": "青空文庫"
              }
            },
            {
              "text": "そのいわれより疾翔と申さるる、大力というは、お徳によって、たとえ火の中水の中、ただこの菩薩を念ずるものは、捨身大菩薩、必らず飛び込んで、お救いになり、その浄明の天上にお連れなさる、その時火に入って身の毛一つも傷かず、水に潜って、羽、塵ほどもぬれぬという、そのお徳をば、大力とこう申しあげるのじゃ。",
              "citation": {
                "source": "二十六夜",
                "author": "宮沢賢治",
                "note": "青空文庫"
              }
            },
            {
              "text": "私はいい所へお連れしようと思って、あなたのお年までお尋ねしたのです。",
              "citation": {
                "source": "さるのこしかけ",
                "author": "宮沢賢治",
                "note": "青空文庫"
              }
            },
            {
              "text": "アノ……どうぞお連れなすって……ホホホホホホ」",
              "citation": {
                "source": "女坑主",
                "author": "夢野久作",
                "note": "青空文庫"
              }
            },
            {
              "text": "なにとぞ王宮へ皇子をこのままの姿でお連れ下さいまし」　皆は、王子の顔が王様とこの森の精の女によく似ているのに気がついて、皆ひれ伏してお辞儀をした。",
              "citation": {
                "source": "犬の王様",
                "author": "夢野久作",
                "note": "青空文庫"
              }
            },
            {
              "text": "どうぞ何処へなり、一緒にお連れなすって下さいまし。",
              "citation": {
                "source": "阿難と呪術師の娘",
                "author": "岡本かの子",
                "note": "青空文庫"
              }
            },
            {
              "text": "ええ、唯今の女が、廊下をお連れ申したでござります。",
              "citation": {
                "source": "伊勢之巻",
                "author": "泉鏡花",
                "note": "青空文庫"
              }
            },
            {
              "text": "」「お召ものの飾から、光の射すお方を見たら、お連れ申して参りますように、お使でございます。",
              "citation": {
                "source": "伊勢之巻",
                "author": "泉鏡花",
                "note": "青空文庫"
              }
            },
            {
              "text": "」「どうぞ、その、その前に先生、どこへか、人の居ない、谷底か、山の中か、島へでも、巌穴へでも、お連れなすって下さいまし。",
              "citation": {
                "source": "悪獣篇",
                "author": "泉鏡花",
                "note": "青空文庫"
              }
            },
            {
              "text": "あなたも厭だといふし、其に私も、そりや樣子を知つて居て、一所に苦勞をして呉れたからツたつても、※さんには極が惡くツて、内へお連れ申すわけには行かないしさ。",
              "citation": {
                "source": "三尺角拾遺",
                "author": "泉鏡花",
                "note": "青空文庫"
              }
            },
            {
              "text": "といいつつ女房を見返りて、「おい、御女中をお連れ申して進ぜなさいと、命つけられて内儀は恐々手を曳いて導けば、怪しき婦人は逆らわず、素直に夫婦に従いて、さもその情を謝するがごとく秋波斜めに泰助を見返り見返り、蹌踉として出行きぬ。",
              "citation": {
                "source": "活人形",
                "author": "泉鏡花",
                "note": "青空文庫"
              }
            },
            {
              "text": "おまゐりをなされまし、……おゝ、お連れがござりましたの。",
              "citation": {
                "source": "深川淺景",
                "author": "泉鏡太郎",
                "note": "青空文庫"
              }
            },
            {
              "text": "若いものは若い同士、本家の方へお連れ申して、土用正月、歌留多でも取って遊ぶが可い、嫁もさぞ喜ぼう、と難有いは、親でのう。",
              "citation": {
                "source": "草迷宮",
                "author": "泉鏡花",
                "note": "青空文庫"
              }
            },
            {
              "text": "「旦那、その喜多八さんを何んでお連れなさりませんね。",
              "citation": {
                "source": "歌行燈",
                "author": "泉鏡花",
                "note": "青空文庫"
              }
            },
            {
              "text": "薄衣　　石山寺參詣のかへり途に、ついそこで旅の御出家樣にお逢ひ申しましたれば、お連れ申してまゐりました。",
              "citation": {
                "source": "佐々木高綱",
                "author": "岡本綺堂",
                "note": "青空文庫"
              }
            },
            {
              "text": "わたくしも立会人を連れて参りませんから、あなたもお連れにならないように希望いたします。",
              "citation": {
                "source": "女の決闘",
                "author": "太宰治",
                "note": "青空文庫"
              }
            },
            {
              "text": "」　Ｈ屋の若主人は（好いお連れ様で）と云わんばかりにやや同業者の葉子達の方を見た。",
              "citation": {
                "source": "鶴は病みき",
                "author": "岡本かの子",
                "note": "青空文庫"
              }
            },
            {
              "text": "忘れも致しませぬ、二十三日の午剋、尼御台さまは御台所さまをお連れになつて御寝所へお見舞ひにおいでになりました。",
              "citation": {
                "source": "右大臣実朝",
                "author": "太宰治",
                "note": "青空文庫"
              }
            },
            {
              "text": "空いつの間にか曇りてポツリ／＼顔におつれどさしたる事もなければ行手を急いで上へ／＼と行く。",
              "citation": {
                "source": "半日ある記",
                "author": "寺田寅彦",
                "note": "青空文庫"
              }
            },
            {
              "text": "――おつれはもう間に合ひません。",
              "citation": {
                "source": "雨ふり",
                "author": "泉鏡太郎",
                "note": "青空文庫"
              }
            },
            {
              "text": "今日、森へ遊びにお姫様をおつれ申しましたところ、道にまよってとうとうここへきてしまいました。",
              "citation": {
                "source": "巨男の話",
                "author": "新美南吉",
                "note": "青空文庫"
              }
            },
            {
              "text": "「おつれさまですかね。",
              "citation": {
                "source": "のら犬",
                "author": "新美南吉",
                "note": "青空文庫"
              }
            },
            {
              "text": "」「その御縁で、ついこの間、糸七さんと、もう一人おつれになって、神保町辺へ用達においでなさいましたお帰りがけ、ご散歩かたがた、「どうだい、新店は立行くかい。",
              "citation": {
                "source": "薄紅梅",
                "author": "泉鏡花",
                "note": "青空文庫"
              }
            }
          ]
        }
      }
    ],
    "relations": {
      "homophones": [],
      "synonyms": [],
      "antonyms": [],
      "related": []
    },
    "meta": {
      "version": "1.0.0",
      "source": "JMdict, Aozora-Crawler, Illusions-Core",
      "updated_at": "2026-03-22T22:30:00Z"
    }
  }
]