[
  {
    "uuid": "f34b29f4-9e4e-546e-8745-cb3da1e4f12a",
    "entry": "驚く",
    "reading": {
      "primary": "おどろく",
      "alternatives": [],
      "is_heteronym": false
    },
    "grammar": {
      "pos": [
        "動詞-五段-カ行",
        "動詞-自動詞"
      ],
      "ctype": null,
      "inflections": null
    },
    "definitions": [
      {
        "index": 1,
        "gloss": "to be surprised",
        "register": "standard",
        "nuance": null,
        "scenarios": [],
        "sensory_tags": {
          "colors": [],
          "temperature": null,
          "sounds": [],
          "emotions": []
        },
        "collocations": [],
        "examples": {
          "standard": [
            {
              "text": "例句",
              "source": "幻辞"
            }
          ],
          "literary": [
            {
              "text": "僕は彼の詩集、「春と修羅」を十年来愛読してゐますが、自分が無名のために、此の地方で印刷された驚くべき詩集を、皆さんにお知らせする術を持ちませんでした。",
              "citation": {
                "source": "宮沢賢治全集刊行に際して",
                "author": "中原中也",
                "note": "青空文庫"
              }
            },
            {
              "text": "彼の神経は、近代文明の病癖を受けて針のやうに過敏であり、その感覚は驚くべく洗練された者であるにも関らず、彼の精神は全く子供のやうな単純さと、野蛮人のやうな生生した原始的の驚きに充たされて居る。",
              "citation": {
                "source": "愛の詩集",
                "author": "愛の詩集の終りに",
                "note": "青空文庫"
              }
            },
            {
              "text": "が、それにも関らず、私は此の詩集に現はれた、彼の驚くべき表現と、そのすばらしい人格的感情のリズムの前には、偽りなき敬虔の心で頭をさげざるを得ないものである。",
              "citation": {
                "source": "愛の詩集",
                "author": "愛の詩集の終りに",
                "note": "青空文庫"
              }
            },
            {
              "text": "彼は常識的な人物でありながら、どこにか驚くべく超常識的な、アナアキスチックの本能感をかくしてゐる。",
              "citation": {
                "source": "芥川龍之介の死",
                "author": "萩原朔太郎",
                "note": "青空文庫"
              }
            },
            {
              "text": "そんなに絢爛たる面貌にくらべて、四肢の貧しさは、これまた驚くべきほどであった。",
              "citation": {
                "source": "ダス・ゲマイネ",
                "author": "太宰治",
                "note": "青空文庫"
              }
            },
            {
              "text": "注意せよ、彼は以前には驚くべく観念明晰な男であつたが、やがてその観念を自己の裡に位置せしめる底のもの、即ち自然――手を差伸べもしないが手を退きもしないもの、――が人間の裡にあつては恩愛的な作用をつとめる、その作用を、雑念或は意識及び其の惰性によつて忘失したのである。",
              "citation": {
                "source": "詩に関する話",
                "author": "中原中也",
                "note": "青空文庫"
              }
            },
            {
              "text": "しかも童話の世界では、それらの機械や武器やが、驚くべきフアンタジイの空想力で、荒唐無稽にまで夢幻化されてゐるのである。",
              "citation": {
                "source": "童話と教育について",
                "author": "萩原朔太郎",
                "note": "青空文庫"
              }
            },
            {
              "text": "すべての驚くべき科學的大發明は、最も子供らしき夢の熱意と、最も荒唐無稽なフアンタジイから誕生した。",
              "citation": {
                "source": "童話と教育について",
                "author": "萩原朔太郎",
                "note": "青空文庫"
              }
            },
            {
              "text": "飛尽す鳥ひとつづつ秋の暮　芭蕉の名句「何にこの師走の町へ行く鴉」には遠く及ばず、同じ蕪村の句「麦秋や何に驚く屋根の鶏」にも劣っているが、やはりこれにも蕪村の蕪村らしいポエジイが現れており、捨てがたい俳句である。",
              "citation": {
                "source": "郷愁の詩人　与謝蕪村",
                "author": "萩原朔太郎",
                "note": "青空文庫"
              }
            },
            {
              "text": "『喧嘩だ、喧嘩だ、』背中を突かれて驚く男、袂をくぐられて間誤付く女、跳ね飛ばされて泣くは子供、足下を攫はれて轉ぶが年寄、呆氣に取られた人人の間を縫て、矢の樣に走つて行く一人の男。",
              "citation": {
                "source": "二十三夜",
                "author": "萩原朔太郎",
                "note": "青空文庫"
              }
            },
            {
              "text": "それを予め知っておらぬと細君も驚く事があるかも知れぬが根が気安過ぎるからの事である故驚く事はない。",
              "citation": {
                "source": "根岸庵を訪う記",
                "author": "寺田寅彦",
                "note": "青空文庫"
              }
            },
            {
              "text": "夢魂いつしか飛んで赴く処は鷹城のほとりなりけん、なつかしき人々の顔まざ／＼と見ては驚く舷側の潮の音。",
              "citation": {
                "source": "東上記",
                "author": "寺田寅彦",
                "note": "青空文庫"
              }
            },
            {
              "text": "仕事が忙しかったり、つい病気したりしていると、いつのまにか柳が芽を吹いたり、桜のつぼみのふくらむのを知らないでいて、急に気がついて驚く事がある。",
              "citation": {
                "source": "春六題",
                "author": "寺田寅彦",
                "note": "青空文庫"
              }
            },
            {
              "text": "化学的の分析と合成は次第に精微をきわめて驚くべき複雑な分子や膠質粒が試験管の中で自由にされている。",
              "citation": {
                "source": "春六題",
                "author": "寺田寅彦",
                "note": "青空文庫"
              }
            },
            {
              "text": "明治十七、八年頃の片田舎の裁判所の書記生にしては実に驚くべきハイカラであったに相違ないのである。",
              "citation": {
                "source": "重兵衛さんの一家",
                "author": "寺田寅彦",
                "note": "青空文庫"
              }
            },
            {
              "text": "」　浦島は龜の驚くべき饒舌に閉口し切つてゐたが、しかし、その最後の一言に、ふと心をひかれた。",
              "citation": {
                "source": "お伽草紙",
                "author": "太宰治",
                "note": "青空文庫"
              }
            },
            {
              "text": "他人の家に、憇ひの巣を期待するのが、そもそも馬鹿者の證據なのかも知れないが、とかくこの訪問といふ事に於いては、吾人は驚くべき思ひ違ひをしてゐるものである。",
              "citation": {
                "source": "お伽草紙",
                "author": "太宰治",
                "note": "青空文庫"
              }
            },
            {
              "text": "それこそ富士という彫刻品の、線と面の回転だ、そこに驚くべき変化と偉大さを発見するだろう。",
              "citation": {
                "source": "不尽の高根",
                "author": "小島烏水",
                "note": "青空文庫"
              }
            },
            {
              "text": "それがまた驚くべく長大なる、最新の熔岩流をひろげて、下吉田の町まで肉薄する剣丸尾、青木ヶ原の樹海から精進村まで、末広がりに扉開きになる青木ヶ原丸尾を、眼下に展開する。",
              "citation": {
                "source": "不尽の高根",
                "author": "小島烏水",
                "note": "青空文庫"
              }
            },
            {
              "text": "それが甲斐と信濃の境、鳳来附近から、一気に押し寄せて来ているのだから驚く。",
              "citation": {
                "source": "不尽の高根",
                "author": "小島烏水",
                "note": "青空文庫"
              }
            },
            {
              "text": "この選手にこと欠かないから驚く。",
              "citation": {
                "source": "運動会の風景",
                "author": "葉山嘉樹",
                "note": "青空文庫"
              }
            },
            {
              "text": "その中に、（見当のつかなかった小僧）が小荷物受渡台の上に彼自身でさえ驚くような敏捷さで、飛び上った。",
              "citation": {
                "source": "乳色の靄",
                "author": "葉山嘉樹",
                "note": "青空文庫"
              }
            },
            {
              "text": "その悪路を子等は驚く程、足早に歩いた。",
              "citation": {
                "source": "氷雨",
                "author": "葉山嘉樹",
                "note": "青空文庫"
              }
            },
            {
              "text": "何と驚くべき空間網ではないか。",
              "citation": {
                "source": "年賀状",
                "author": "寺田寅彦",
                "note": "青空文庫"
              }
            },
            {
              "text": "これに反して振り返って見た月日の経過はまた自分ながら驚くほどに早いものに思われた。",
              "citation": {
                "source": "厄年と etc.",
                "author": "寺田寅彦",
                "note": "青空文庫"
              }
            },
            {
              "text": "そこで今度は声を立てないで口を自由に且つ充分に動かして読む真似をしてみると、その歌の口調のあらゆる特徴が驚くほど鮮明に頭に響いて来るのである。",
              "citation": {
                "source": "歌の口調",
                "author": "寺田寅彦",
                "note": "青空文庫"
              }
            },
            {
              "text": "近頃ベルギーの天文台年報にストローバンという人が出した「銀河に対する星の分布」と題する論文の抜書を見ると、驚くべき学者の根気の結果が現われている。",
              "citation": {
                "source": "天河と星の数",
                "author": "寺田寅彦",
                "note": "青空文庫"
              }
            },
            {
              "text": "少しずつと云うのは遠い地球から見て云う事で実は驚くべき速度で動いている、がどの星もみなリーラ星宿から外へ向いて散開しつつあるように見える。",
              "citation": {
                "source": "宇宙の二大星流",
                "author": "寺田寅彦",
                "note": "青空文庫"
              }
            },
            {
              "text": "この驚くべく長い管で出来た電灯は、その発明者ディー・マクファーラン・ムーアの名に依ってムーア灯と名づけられている。",
              "citation": {
                "source": "ムーア灯",
                "author": "寺田寅彦",
                "note": "青空文庫"
              }
            },
            {
              "text": "麦秋や何におどろく屋根の鶏　農家の屋根の上に飛びあがって、けたたましく啼いてる鶏は、何に驚いたのであろう。",
              "citation": {
                "source": "郷愁の詩人　与謝蕪村",
                "author": "萩原朔太郎",
                "note": "青空文庫"
              }
            }
          ]
        }
      },
      {
        "index": 2,
        "gloss": "to be frightened",
        "register": "standard",
        "nuance": null,
        "scenarios": [],
        "sensory_tags": {
          "colors": [],
          "temperature": null,
          "sounds": [],
          "emotions": []
        },
        "collocations": [],
        "examples": {
          "standard": [
            {
              "text": "例句",
              "source": "幻辞"
            }
          ],
          "literary": []
        }
      }
    ],
    "relations": {
      "homophones": [],
      "synonyms": [],
      "antonyms": [],
      "related": []
    },
    "meta": {
      "version": "1.0.0",
      "source": "JMdict, Aozora-Crawler, Illusions-Core",
      "updated_at": "2026-03-22T22:30:00Z",
      "freq_rank": 3072
    }
  }
]